pyaudiocook/__init__.py
pyaudiocook/audio_recorder.py
pyaudiocook/audio_transcriber.py
pyaudiocook-1.0.2.dist-info/LICENSE
pyaudiocook-1.0.2.dist-info/METADATA
pyaudiocook-1.0.2.dist-info/WHEEL
pyaudiocook-1.0.2.dist-info/RECORD
