Metadata-Version: 2.1
Name: pyaudiocook
Version: 1.0.2
Summary: A Python package for audio recording and transcribing
Author: Jesse Wei
Author-email: jesseweijapan@gmail.com
Requires-Python: >=3.11,<4.0
Classifier: Programming Language :: Python :: 3
Classifier: Programming Language :: Python :: 3.11
Classifier: Programming Language :: Python :: 3.12
Requires-Dist: numpy (>=2.0.0,<3.0.0)
Requires-Dist: openai (>=1.42.0,<2.0.0)
Requires-Dist: sounddevice (>=0.5.0,<0.6.0)
Requires-Dist: whisper (>=1.1.10,<2.0.0)
